deepstack/__init__.py
deepstack/base.py
deepstack/ensemble.py
deepstack-0.0.9.dist-info/LICENSE
deepstack-0.0.9.dist-info/METADATA
deepstack-0.0.9.dist-info/WHEEL
deepstack-0.0.9.dist-info/top_level.txt
deepstack-0.0.9.dist-info/RECORD
