Metadata-Version: 2.1
Name: deepstack
Version: 0.0.9
Summary: DeepStack: Ensembles for Deep Learning
Home-page: https://github.com/jcborges/DeepStack
Maintainer: Julio Borges
License: MIT
Download-URL: https://github.com/jcborges/DeepStack/archive/v_0.0.9.tar.gz
Platform: UNKNOWN
Requires-Dist: numpy (>=1.16.4)
Requires-Dist: keras (>=2.2.5)
Requires-Dist: tensorflow (>=1.14.0)
Requires-Dist: scikit-learn (>=0.21.2)
